recaptcha2
